simimg-0.9.8.dist-info/METADATA
simimg-0.9.8.dist-info/WHEEL
simimg-0.9.8.dist-info/entry_points.txt
simimg-0.9.8.dist-info/licenses/LICENSE
simimg/__init__.py
simimg/classes/.ruff_cache/.gitignore
simimg/classes/.ruff_cache/CACHEDIR.TAG
simimg/classes/conditionmodules.py
simimg/classes/configuration.py
simimg/classes/controller.py
simimg/classes/customscales.py
simimg/classes/fileobject.py
simimg/classes/imageframe.py
simimg/classes/miscmodules.py
simimg/classes/scrollframe.py
simimg/classes/toolbar.py
simimg/classes/tooltip.py
simimg/dialogs/.ruff_cache/.gitignore
simimg/dialogs/.ruff_cache/CACHEDIR.TAG
simimg/dialogs/configurationwindow.py
simimg/dialogs/confirmdeletedialog.py
simimg/dialogs/infowindow.py
simimg/dialogs/viewer.py
simimg/icons/add.png
simimg/icons/delete.png
simimg/icons/exit.png
simimg/icons/hide.png
simimg/icons/info.png
simimg/icons/move.png
simimg/icons/open.png
simimg/icons/play.png
simimg/icons/refresh.png
simimg/icons/settings.png
simimg/icons/simimg.png
simimg/icons/uncheck.png
simimg/simimg.py
simimg/utils/.ruff_cache/.gitignore
simimg/utils/.ruff_cache/0.2.1/17781272156839724043
simimg/utils/.ruff_cache/0.2.1/2219549764661831005
simimg/utils/.ruff_cache/0.2.2/13281178302887887878
simimg/utils/.ruff_cache/CACHEDIR.TAG
simimg/utils/database.py
simimg/utils/handyfunctions.py
simimg/utils/pillowplus.py
simimg/utils/pooling.py
simimg-0.9.8.dist-info/RECORD
