Metadata-Version: 2.1
Name: simimg
Version: 0.9.8
Summary: Similar Image Finder
Author-Email: sacha <sachahony@gmail.com>, Sacha Hony <zazahohonini@gmail.com>
License: MIT
Classifier: License :: OSI Approved :: MIT License
Classifier: Operating System :: OS Independent
Classifier: Programming Language :: Python :: 3
Project-URL: Homepage, https://github.com/zazaho/SimImg
Requires-Python: >=3
Requires-Dist: Pillow
